{
  "id": "cinderella",
  "juvenile_text": "昔々、シンデレラと呼ばれている美しく心の優しい娘がいました。 シンデレラのお母さんはなくなり、お父さんは新しいお母さんと結婚しましたが、２番目のお母さんはとても意地悪で、さらにその連れ子である二人の義理のお姉さまからもその美しさを妬まれ、掃除、洗濯、食事の支度などすべてシンデレラにやらせていました。ある時、この国の王子様が舞踏会を開く事になり、二人の義理のお姉さまはドレスを着てお城へ出かけていきました。 シンデレラも行きたかったのですが、もちろん連れて行ってもらえず、一人になり悲しくなったシンデレラは泣き出してしまいました。「わたしも舞踏会に行きたいわ」すると、シンデレラの目の前に魔法使いが現れ、「泣かないで、シンデレラ、私が舞踏会へ連れて行ってあげるわ」「本当？でも、こんな服では行けないわ」そういうと、魔法使いは魔法の杖を振り、素敵なドレスを用意してくれました。「それからシンデレラ、畑でカボチャを取っておいで」シンデレラが畑からカボチャを取ってきて、魔法使いがそのカボチャを叩くと、カボチャがどんどん大きくなり、何と黄金の馬車になったではありませんか。「まあ、立派な馬車。すてき」「まだまだ、これからよ。馬車を引くには、馬が必要よ。そこに、ハツカネズミが六匹いるわね」魔法使いはハツカネズミをつかまえ、魔法のつえでハツカネズミにさわると、ネズミはみるみるうちに、立派な白馬になりました。 それから大きな灰色ネズミを一匹連れてきて、「このネズミは・・・」そういうと、今度は立派なおひげをした太っちょ運転手に早変わりです。「シンデレラ、次はトカゲを六匹集めておくれ」「はい」シンデレラが集めたトカゲは、魔法のつえでお供の人になりました。「ほらね。ドレスに、馬車に、白馬に、運転手に、お供。さあシンデレラ、これで舞踏会に行く仕度が出来たわよ。それからこのガラスのクツを。」そういって魔法使いは、シンデレラに小さくて素敵なガラスのクツをわたしました。美しいドレス、かぼちゃから作った豪華な馬車、きらめくガラスの靴、シンデレラはとても喜びました。最後に魔法使いはシンデレラに１つだけ注意を与えました「１２時を過ぎれば馬車もドレスも魔法が解けて元の姿に戻ってしまうから、必ず１２時までには戻ってきなさい。」「わかりました。かならず１２時に戻ってきます。」シンデレラはそう約束して、大喜びで舞踏会へ出かけました。さて、舞踏会に着いた美しいシンデレラは、たちまちみんなの注目の的となり、王子様もシンデレラの美しさに気づき、シンデレラを踊りに誘いました。「ぼくと、踊っていただけませんか？」「もちろんです。王子様」シンデレラは王子様と夢のような時間を過ごしているうちに、時の経つのも忘れてしまい、気がつくと、時計が１２時を打ち始めています。 魔法使いとの約束を思い出したシンデレラは駆け出しました。「まあ大変、１２時だわ。もう帰らなくては。」まだシンデレラがどこの誰だか聞いていなかった王子様は引き留めようとしましたが、シンデレラはあっという間に消えてしまいました。 階段にはシンデレラが履いていた美しいガラスの靴が片方だけ残されていました。 王子様は何とかしてあの舞踏会の女性を探し出そうと、おふれを出しました。 ガラスの靴がぴったり合う女性を自分の妻にする、というので、身分の高い女性から次々にガラスの靴を試してみましたが、ガラスの靴がぴったり合う女性は誰もいませんでした。 王子様の使いはシンデレラの家にもやってきて、義理のお姉さまたちも靴を試しますが、何とかしてガラスの靴を履こうと無理をしましたが、無駄でした。 そこへシンデレラが進み出て、王子様のお使いに、「私にもクツをはかせていただけませんか」と頼みました。「何をバカな事を言っているの」そう義理のお姉さまたちはいいましたが、お使いはシンデレラにも履かせてみると、ガラスの靴はまるでシンデレラのために作ったかのようにぴったりでした。 お使いは、この方こそ王子様の探しておられた女性だ、と言って、シンデレラをお城へ連れていき、シンデレラは王子さまと結婚して、いつまでも幸せに暮らしました。",
  "kind": "fairytale",
  "language": "ja",
  "opening_seed": "娘は灰だらけの手を洗い、公民館の明かりを遠くから見上げた。",
  "public_domain": true,
  "setting": "町なかの家と公民館の祝賀会",
  "source_label": "グリム童話",
  "spec": {
    "skeleton": {
      "canonical_motifs": [
        "灰まみれ",
        "舞踏会",
        "変身",
        "夜更け",
        "片方の靴"
      ],
      "role_constraints": [
        "虐げられる娘",
        "彼女を助ける力",
        "彼女を見いだす王子",
        "抑圧する家族"
      ],
      "taboo_or_rule": "外見や地位だけで他者の価値を決めないこと",
      "reward_punishment": "押さえ込まれた人が一夜だけ可視化され、最後に選び直される",
      "emotional_aftertaste": "華やかさのあとに長い抑圧の影が残る",
      "recognition_cues": [
        "灰",
        "舞踏会",
        "夜更け",
        "靴"
      ],
      "required_beats": [
        {
          "id": "oppress",
          "label": "灰まみれの抑圧"
        },
        {
          "id": "ball",
          "label": "華やかな場へ行く"
        },
        {
          "id": "midnight",
          "label": "夜更けに去る"
        },
        {
          "id": "shoe",
          "label": "靴で見つけられる"
        }
      ]
    },
    "twists": {
      "role_shift": "抑圧する者と耐える者の間にある静かな力の構造",
      "view_shift": "真の身分をどこから見るかという問い",
      "value_shift": "美しさと徳のどちらが報われるべきかという問い",
      "inversion": "この物語の変身が時限制でなかったら何が残るか",
      "scale_shift": "身分の差が及ぶ範囲を変えたとき、何が見えるか"
    }
  },
  "text": "昔々、やさしく勤め者の娘がいました。幼い頃に母を亡くし、父が再婚した継母と二人の義姉は心が意地悪で、娘にみすぼらしい服を着せ、台所の灰の中に座らせ、炊事、洗濯、掃除、馬小屋の世話と、朝から晩まで働かせました。夜になると娘は疲れ果てて暖炉の灰の中で眠るのが常でしたから、いつしかシンデレラと呼ばれるようになりました。唯一の慰めは、庭の母の墓に植えた榛の木の傍らに白い鳩が来ることで、シンデレラが木の下で泣くと鳩がやってきて羽を広げてくれました。ある日、王様から国中の乙女を招く舞踏会の知らせが届きました。王子様の花嫁を探すためです。継母と義姉たちは大騒ぎして着飾りましたが、シンデレラには「おまえは汚い灰かぶり、行かせるものか」と言いました。一人残されたシンデレラが母の墓の榛の木の下で泣いていると、白い鳩が舞い降り、金と銀に輝くドレスとガラスの靴を運んできました。シンデレラが着替えると見違えるほど美しくなり、鳩が馬車も用意してくれました。「十二時の鐘が鳴る前に必ず帰りなさい」と声が聞こえました。お城に現れた見知らぬ美しい姫に、王子様はひと目で心を奪われ、他の誰とも踊らず、夜中ずっとシンデレラだけと踊り続けました。しかし十二時の鐘の音が響き始めると、シンデレラはあわてて逃げ出し、階段でガラスの靴を一つ落としてしまいました。王子様はシンデレラの素性も名前も知りません。残ったガラスの靴だけを手がかりに、王子様は家来を連れて国中を訪ね歩きました。継母と義姉たちが靴を履こうとしても足が入りません。最後にシンデレラが試すとぴったりと合いました。するとあの白い鳩が空から金のドレスを運んできて、シンデレラの姿はたちまち舞踏会の夜の美しい姫に戻りました。王子様はシンデレラを認め、喜んで馬車に乗せてお城へ連れていきました。二人は結婚して幸せに暮らしました。お城での生活はシンデレラにとって何もかもが驚きでした。しかし一番驚いたのは、王子様が煌びやかな舞踏会の中ではなく、庭を二人で歩きながらシンデレラのことを本当に知ろうとしてくれたことでした。シンデレラは継母の家での日々のこと、亡き母のこと、榛の木の下で泣きながら白い鳩と話したことを少しずつ語りました。王子様はじっと耳を傾けて聞いてくれました。継母と義姉たちはシンデレラが王子様の花嫁になると知り、態度を一変させましたが、シンデレラは彼女たちを恨みませんでした。「過去のことは過去のこと。これからを大切にしたい」とシンデレラは言いました。その広い心は王様からも王妃様からも愛され、シンデレラはやがて誰にでも分け隔てなく接する、国中に慕われる王妃となりました。亡きお母さんの魂が宿っているかのような榛の木は、お城の庭に移し植えられ、毎年春に白い花を咲かせたということです。",
  "title": "シンデレラ"
}
