{
  "id": "issun",
  "juvenile_text": "昔、昔あるところにおじいさんとおばあさんが住んでいました。子供のない二人は毎日子供が授かるよう神様に祈っていました。「神様、どうか私たちに子供を授けてください。どんな小さな子供でも構いません。」ある日、驚いたことに、二人に小さな赤ん坊が授かりました。背の高さ一寸にも満たない男の子です。さっそく赤ん坊に一寸法師と名付け、二人は宝物のように育てました。一寸法師はたくましい頭のいい子供になり、ある日二人にこう言いました。「お父さん、お母さん、私に針と藁とおわんと箸を下さい。」「一体どうする気ですか。」とおばあさん。「針は剣、藁はさや、おわんは船、箸はかいです。都に行って武士になるつもりです。」二人は許しを上げました。さっそく一寸法師は都へと向かいました。途中、一寸法師はありに会い、「ありさん、川はどこですか。」「たんぽぽ畑のところです。」一寸法師は川につくと、おわんに飛び乗り、矢のように川を下っていきました。途中で魚が一寸法師を食べ物だと間違えて向かって来ました。一寸法師は箸をつかって魚を追い払いました。波に揺られ、雨にうたれ、風に吹かれ、やっとのことで都に着きました。誇らしげに町を歩いていくと大きな立派な家が見え、一寸法師はそこで働くことを思いつきました。「門を開けてください。お願いがあります。」主人は門をあけるとあたりを見回しましたが誰もいません。「一体だれだ。誰も見えんぞ。」「あなたの足元にいます。」主人は下駄のそばに一寸法師を見つけ、「私は一寸法師と申します。ここで働かせてもらいたいと思います。」「お前はなかなか活発で頭が良さそうだ。よし家来にしてやろう。」そうして働くことになった家には美しい娘がおり、一寸法師はその娘から読み書きを教わりました。一寸法師は頭が良くてすぐ理解してしまいました。ある日、娘は一寸法師を連れてお宮参りに出かけた途中、大きな鬼に出会いました。鬼は娘をさらいに来たのです。「悪い鬼め。お嬢さんにちょっとでも手を出せばただではおかないぞ。」「生意気な。食べてしまうぞ。」と鬼は言うと一気に一寸法師を飲み込んでしまいましたが、「いたた、いたたたた．．．」一寸法師は針でお腹の中を刺しました。「いたた。死んでしまう。降参だ。助けてくれ。」鬼は一寸法師を吹き出すと山の方へ一目散に逃げて行きました。「助けてくれてありがとう。あなたは小さいけど、とても勇敢で強いのね。」「ちっと見てください。鬼が何か忘れていきました。これは何でしょう。」「これはうちでの小槌というものです。これを振ると欲しいものが何でも手に入ります。一寸法師、あなたは何が欲しいですか。」「私は大きくなりたいです。」うちでの小槌をふると、一寸法師はぐんぐん大きくなりあっと言う間に立派な大人になりました。一寸法師は娘さんと結婚し、望んだ通り立派な武士になりました。",
  "kind": "folktale",
  "language": "ja",
  "opening_seed": "一寸ほどの背丈しかない若者は、椀のように小さな舟を押して町へ向かった。",
  "public_domain": true,
  "setting": "下町の長屋と小さな店",
  "source_label": "日本昔話",
  "spec": {
    "skeleton": {
      "canonical_motifs": [
        "小さな体",
        "針の刀",
        "椀の舟",
        "鬼の腹",
        "打ち出の小槌"
      ],
      "role_constraints": [
        "小さな主役",
        "守る姫",
        "巨大な対立役",
        "成長を可能にする道具"
      ],
      "taboo_or_rule": "小ささを恥じて機転を捨てないこと",
      "reward_punishment": "弱さを知恵に変えた者が最後に伸びる",
      "emotional_aftertaste": "小さな勇気が急に大きく見える",
      "recognition_cues": [
        "一寸",
        "針",
        "椀",
        "小槌",
        "鬼"
      ],
      "required_beats": [
        {
          "id": "depart",
          "label": "小さな旅立ち"
        },
        {
          "id": "serve",
          "label": "姫のそばで働く"
        },
        {
          "id": "fight",
          "label": "巨大な相手の内側で戦う"
        },
        {
          "id": "grow",
          "label": "小槌で変わる"
        }
      ]
    },
    "twists": {
      "role_shift": "身体の小ささと心の大きさが生む非対称な力",
      "view_shift": "小さな者の勇気をどこから評価するか",
      "value_shift": "勇気によって変えた身体的制約の正当性",
      "inversion": "この物語の小ささが強みにならなかったら何が残るか",
      "scale_shift": "身体の大きさが及ぼす影響の範囲を変えたとき、何が見えるか"
    }
  },
  "text": "昔々、摂津の国に子どものない老夫婦がございました。「どうか一人でいいから子どもを授けてください」と住吉の神様に何年も祈り続けたところ、ようやく一人の男の子が生まれました。ところがその子は生まれたときから一寸ほどの大きさで、どれだけ年月がたっても大きくなりませんでした。夫婦は一寸法師と名づけて大事に育てました。体は小さくとも心は人一倍大きく、誰よりも元気でした。十五になったころ、一寸法師は老夫婦に言いました。「わたしは都に出て、お武家に仕えたいと思います。どうか旅立ちをお許しください」。夫婦は心配しましたが、一寸法師の決意は固く、根負けして旅立ちを許しました。おばあさんは針を腰の刀に、お椀を舟に、お箸を棹に用意してくれました。一寸法師はお椀の舟に乗り、お箸で川の水をこいで淀川を下り、都の三条大橋に着きました。大きなお屋敷の前に立ち「仕えさせてください」と叫ぶと、家人に笑われましたが、主人の目に留まり、姫君のお守り役として取り立てられました。一寸法師は指の爪ほどの体で姫の文箱の上に座り、外出の折りには姫の衣の袖の中で揺られながら、鋭い目で周りを見張りました。ある秋の日、姫と清水寺へお参りに行く帰り道のことです。突然大きな鬼が現れ、姫を攫おうとしました。一寸法師は「姫を離せ」と鬼の前に立ちはだかりました。鬼は笑って一寸法師をつまみ上げ、ぱくりと口に入れて飲み込みました。しかし一寸法師は鬼の胃の中でも怯まず、針の刀を振り回して胃の壁を突き刺しました。「痛い、痛い」と鬼が暴れるほど、一寸法師は激しく突き刺し続けました。とうとう鬼は「参った」と叫び、一寸法師を吐き出して逃げていきました。その際に鬼が落としていったのは打ち出の小槌でした。「姫、この小槌で願いをかなえてください」と一寸法師が言うと、姫は小槌を振ってくれました。振るたびに一寸法師はみるみる大きくなり、やがて背の高い立派な若武者の姿になりました。一寸法師はやがて屋敷の主人の婿となり、姫と仲むつまじく末永く幸せに暮らしたといいます。一寸法師が大きくなった日のことを、屋敷の人々は後々まで語りました。打ち出の小槌が振られるたびに、みるみる大きくなっていく姿を、縁側から見ていた使用人たちは目を丸くして声も出なかったといいます。立派な若武者になった一寸法師は、しかし変わらない目をしていました。物怖じしない目、正直な目——小さかったころと同じ目でした。一寸法師はやがて屋敷の主人の婿になりましたが、故郷の老夫婦のことを忘れませんでした。都から便りを送り、仕送りをし、数年に一度は老いた両親を訪ねました。「都に出てお武家に仕えたい」と言い張ったあの日から、老夫婦は息子の言葉通りになったことを誇りに思っていました。住吉の神様に長年祈り続けてようやく授かった、一寸ほどの小さな息子が、今は誰より大きな武者になったのです。一寸法師の話は、小さくても心が大きければ道は開けるという教えとして、今に伝わっています。",
  "title": "一寸法師"
}
